setup.py
resolv/__init__.py
resolv/shared.py
resolv.egg-info/PKG-INFO
resolv.egg-info/SOURCES.txt
resolv.egg-info/dependency_links.txt
resolv.egg-info/top_level.txt
resolv/resolvers/__init__.py
resolv/resolvers/dummy.py
resolv/resolvers/filebox.py
resolv/resolvers/filenuke.py
resolv/resolvers/mediafire.py
resolv/resolvers/onechannel.py
resolv/resolvers/pastebin.py
resolv/resolvers/putlocker.py
resolv/resolvers/sockshare.py
resolv/resolvers/vidbux.py
resolv/resolvers/vidxden.py
resolv/resolvers/youtube.py