Metadata-Version: 1.1
Name: resolv
Version: 1.3.0
Summary: Module for resolving URLs from filehosters, video hosters, and other content hosters
Home-page: http://cryto.net/resolv
Author: Sven Slootweg
Author-email: resolv@cryto.net
License: UNKNOWN
Platform: UNKNOWN
Provides: resolv
